nle_prediction/__init__.py
nle_prediction/create_ordered_dataset.py
nle_prediction/dataloader.py
nle_prediction/dataset.py
nle_prediction/download.py
nle_prediction/preprocessing.py
nle_prediction/setup_cli.py
nle_prediction/visualization.py
nle_prediction-0.1.0.dist-info/licenses/LICENSE
nle_prediction-0.1.0.dist-info/METADATA
nle_prediction-0.1.0.dist-info/WHEEL
nle_prediction-0.1.0.dist-info/entry_points.txt
nle_prediction-0.1.0.dist-info/top_level.txt
nle_prediction-0.1.0.dist-info/RECORD
