Metadata-Version: 2.4
Name: nle-prediction
Version: 0.1.0
Summary: NetHack Prediction Benchmark - A dataset and dataloader for testing streaming learning algorithms on ordered NetHack game data
Author: Edan Meyer
Maintainer: Edan Meyer
License: MIT
Keywords: nethack,machine-learning,dataset,streaming-learning,benchmark
Classifier: Development Status :: 3 - Alpha
Classifier: Intended Audience :: Science/Research
Classifier: Programming Language :: Python :: 3
Classifier: Programming Language :: Python :: 3.8
Classifier: Programming Language :: Python :: 3.9
Classifier: Programming Language :: Python :: 3.10
Classifier: Programming Language :: Python :: 3.11
Classifier: Topic :: Scientific/Engineering :: Artificial Intelligence
Requires-Python: >=3.8
License-File: LICENSE
Requires-Dist: nle>=1.2.0
Requires-Dist: numpy>=1.20.0
Requires-Dist: requests>=2.25.0
Requires-Dist: tqdm>=4.60.0
Dynamic: license-file
